riscemu/IO/IOModule.py
riscemu/IO/TextIO.py
riscemu/IO/__init__.py
riscemu/__init__.py
riscemu/__main__.py
riscemu/assembler.py
riscemu/colors.py
riscemu/config.py
riscemu/core/__init__.py
riscemu/core/binary_data_memory_section.py
riscemu/core/cpu.py
riscemu/core/csr.py
riscemu/core/csr_constants.py
riscemu/core/exceptions.py
riscemu/core/flags.py
riscemu/core/float.py
riscemu/core/instruction.py
riscemu/core/instruction_context.py
riscemu/core/instruction_memory_section.py
riscemu/core/int32.py
riscemu/core/memory_section.py
riscemu/core/mmu.py
riscemu/core/platform.py
riscemu/core/privmodes.py
riscemu/core/program.py
riscemu/core/program_loader.py
riscemu/core/registers.py
riscemu/core/rtclock.py
riscemu/core/simple_instruction.py
riscemu/core/traps.py
riscemu/core/usermode_cpu.py
riscemu/debug.py
riscemu/decoder/__init__.py
riscemu/decoder/__main__.py
riscemu/decoder/decoder.py
riscemu/decoder/formats.py
riscemu/decoder/formatter.py
riscemu/decoder/instruction_table.py
riscemu/decoder/regs.py
riscemu/helpers.py
riscemu/instructions/RV32A.py
riscemu/instructions/RV32D.py
riscemu/instructions/RV32F.py
riscemu/instructions/RV32I.py
riscemu/instructions/RV32M.py
riscemu/instructions/RV_Debug.py
riscemu/instructions/Zicsr.py
riscemu/instructions/__init__.py
riscemu/instructions/float_base.py
riscemu/instructions/instruction_set.py
riscemu/interactive.py
riscemu/libc/README.md
riscemu/libc/crt0.s
riscemu/libc/stdlib.s
riscemu/libc/string.s
riscemu/parser.py
riscemu/priv/CSR.py
riscemu/priv/ElfLoader.py
riscemu/priv/ImageLoader.py
riscemu/priv/PrivCPU.py
riscemu/priv/PrivMMU.py
riscemu/priv/PrivRV32I.py
riscemu/priv/__init__.py
riscemu/priv/__main__.py
riscemu/priv/types.py
riscemu/py.typed
riscemu/riscemu_main.py
riscemu/syscall.py
riscemu/tokenizer.py
riscemu/tools/riscemu
riscemu-2.2.7.dist-info/LICENSE
riscemu-2.2.7.dist-info/METADATA
riscemu-2.2.7.dist-info/WHEEL
riscemu-2.2.7.dist-info/entry_points.txt
riscemu-2.2.7.dist-info/RECORD
