Metadata-Version: 2.1
Name: riscemu
Version: 2.2.7
Summary: A basic RISC-V emulator
Home-page: https://github.com/antonlydike/riscemu
License: MIT
Keywords: RISC-V
Author: Anton Lydike
Author-email: me@antonlydike.de
Requires-Python: >=3.8,<4.0
Classifier: License :: OSI Approved :: MIT License
Classifier: Operating System :: OS Independent
Classifier: Programming Language :: Python :: 3
Classifier: Programming Language :: Python :: 3.8
Classifier: Programming Language :: Python :: 3.9
Classifier: Programming Language :: Python :: 3.10
Classifier: Programming Language :: Python :: 3.11
Classifier: Programming Language :: Python :: 3.12
Requires-Dist: importlib-resources (>=6.1.0,<7.0.0)
Requires-Dist: pyelftools (>=0.30,<0.31)
Project-URL: Bug Tracker, https://github.com/antonlydike/riscemu/issues
Project-URL: Repository, https://github.com/antonlydike/riscemu
